encar/__init__.py
encar/client.py
encar/config.py
encar/schema.yaml
encar-0.1.4.dist-info/LICENSE
encar-0.1.4.dist-info/METADATA
encar-0.1.4.dist-info/WHEEL
encar-0.1.4.dist-info/RECORD
