Metadata-Version: 2.3
Name: encar
Version: 0.1.4
Summary: encar is the official Python client parser for Carapis Encar API. Use this parser library to access, search, and analyze real-time Korean used car data from Encar.com via a powerful REST API. Supports vehicle listings, details, manufacturers, models, and more.
License: MIT
Keywords: encar,encar api,carapis,korean car api,used car api,vehicle data,car marketplace,car listing,client,automotive,parser,encar parser,data parser
Author: Carapis.com
Author-email: info@carapis.com
Requires-Python: >=3.11,<4.0
Classifier: Development Status :: 4 - Beta
Classifier: Intended Audience :: Developers
Classifier: License :: OSI Approved :: MIT License
Classifier: Operating System :: OS Independent
Classifier: Programming Language :: Python :: 3
Classifier: Programming Language :: Python :: 3.11
Classifier: Programming Language :: Python :: 3.12
Classifier: Programming Language :: Python :: 3.13
Classifier: Topic :: Internet :: WWW/HTTP :: Dynamic Content
Classifier: Topic :: Software Development :: Libraries :: Python Modules
Requires-Dist: python-dotenv (>=1.0.0,<2.0.0)
Requires-Dist: pyyaml (>=6.0.1,<7.0.0)
Requires-Dist: questionary (>=2.1.0,<3.0.0)
Requires-Dist: requests (>=2.31.0,<3.0.0)
Requires-Dist: semver (>=3.0.4,<4.0.0)
Requires-Dist: toml (>=0.10.2,<0.11.0)
Project-URL: Documentation, https://carapis.com/
Project-URL: Homepage, https://carapis.com/
Project-URL: Repository, https://github.com/markolofsen/carapis-encar-pypi
